pictor/__init__.py
pictor/pictor.py
pictor/apps/__init__.py
pictor/apps/luigi/__init__.py
pictor/apps/luigi/edf_viewer.py
pictor/objects/__init__.py
pictor/objects/image/__init__.py
pictor/objects/image/large_image.py
pictor/objects/particle_dynamic/__init__.py
pictor/objects/particle_dynamic/particle_system.py
pictor/objects/protein/__init__.py
pictor/objects/protein/protein.py
pictor/objects/protein/readers.py
pictor/objects/signals/__init__.py
pictor/objects/signals/digital_signal.py
pictor/objects/signals/eeg.py
pictor/objects/signals/scrolling.py
pictor/objects/signals/signal_group.py
pictor/plotters/__init__.py
pictor/plotters/matrix_viewer.py
pictor/plotters/microscope.py
pictor/plotters/monitor.py
pictor/plotters/oscilloscope.py
pictor/plotters/plotter_base.py
pictor/plotters/prompter.py
pictor/plotters/retina.py
pictor/plotters/signal_viewer.py
pictor/plotters/arsenal/__init__.py
pictor/plotters/arsenal/iqscope.py
pictor/plotters/arsenal/sleep_monitor.py
pictor/plugins/__init__.py
pictor/plugins/database.py
pictor/plugins/dialog_utils.py
pictor/plugins/studio.py
pictor/plugins/timer.py
pictor/vinci/__init__.py
pictor/vinci/board.py
pictor/vinci/events.py
pictor/vinci/mind.py
pictor/vinci/vinci.py
pictor/widgets/__init__.py
pictor/widgets/canvas.py
pictor/widgets/outline_bar.py
pictor/widgets/widget_base.py
pictor/xomics/__init__.py
pictor/xomics/feature_explorer.py
pictor/xomics/omix.py
pictor/xomics/stat_analyzers.py
pictor/xomics/stat_annotator.py
pictor/xomics/evaluation/__init__.py
pictor/xomics/evaluation/calibration.py
pictor/xomics/evaluation/confusion_matrix.py
pictor/xomics/evaluation/dca.py
pictor/xomics/evaluation/delong.py
pictor/xomics/evaluation/pipeline.py
pictor/xomics/evaluation/reg_ana.py
pictor/xomics/evaluation/roc.py
pictor/xomics/misc/__init__.py
pictor/xomics/misc/distribution.py
pictor/xomics/ml/__init__.py
pictor/xomics/ml/decision_tree.py
pictor/xomics/ml/elastic_net.py
pictor/xomics/ml/lasso.py
pictor-1.0.0.dist-info/licenses/LICENSE
pictor-1.0.0.dist-info/METADATA
pictor-1.0.0.dist-info/WHEEL
pictor-1.0.0.dist-info/top_level.txt
pictor-1.0.0.dist-info/RECORD
